.gitignore
AUTHORS
LICENSE
MANIFEST.in
NOTICE
README
requirements.txt
setup.py
doc_src/Makefile
doc_src/api.rst
doc_src/conf.py
doc_src/getting_started.rst
doc_src/index.rst
doc_src/installation.rst
doc_src/make.bat
doc_src/markup.rst
doc_src/real_world_example.rst
doc_src/_build/doctrees/api.doctree
doc_src/_build/doctrees/environment.pickle
doc_src/_build/doctrees/getting_started.doctree
doc_src/_build/doctrees/index.doctree
doc_src/_build/doctrees/installation.doctree
doc_src/_build/doctrees/markup.doctree
doc_src/_build/doctrees/real_world_example.doctree
doc_src/_build/doctrees/reference/index.doctree
doc_src/_build/doctrees/reference/settings.doctree
doc_src/_build/doctrees/reference/template_tags.doctree
doc_src/_static/breadcrumb_background.png
doc_src/_static/default.css
doc_src/_static/documentation.png
doc_src/_static/header_sm_mid.png
doc_src/_static/scrn1.png
doc_src/_static/scrn2.png
doc_src/_static/searchfield_leftcap.png
doc_src/_static/searchfield_repeat.png
doc_src/_static/searchfield_rightcap.png
doc_src/_static/title_background.png
doc_src/_static/toc.js
doc_src/_static/triangle_closed.png
doc_src/_static/triangle_left.png
doc_src/_static/triangle_open.png
doc_src/_templates/layout.html
doc_src/reference/index.rst
doc_src/reference/settings.rst
doc_src/reference/template_tags.rst
docs/.buildinfo
docs/api.html
docs/genindex.html
docs/getting_started.html
docs/index.html
docs/installation.html
docs/markup.html
docs/objects.inv
docs/real_world_example.html
docs/search.html
docs/searchindex.js
docs/_sources/api.txt
docs/_sources/getting_started.txt
docs/_sources/index.txt
docs/_sources/installation.txt
docs/_sources/markup.txt
docs/_sources/real_world_example.txt
docs/_sources/reference/index.txt
docs/_sources/reference/settings.txt
docs/_sources/reference/template_tags.txt
docs/_static/basic.css
docs/_static/breadcrumb_background.png
docs/_static/default.css
docs/_static/doctools.js
docs/_static/documentation.png
docs/_static/file.png
supertagging.egg-info/PKG-INFO
supertagging.egg-info/SOURCES.txt
supertagging.egg-info/dependency_links.txt
supertagging.egg-info/requires.txt
supertagging.egg-info/top_level.txt
