Metadata-Version: 1.0
Name: supertagging
Version: 0.5.3
Summary: An interface to the Open Calais service for semantic markup.
Home-page: https://github.com/washingtontimes/django-supertagging
Author: Jose Soares
Author-email: jsoares@washingtontimes.com
License: UNKNOWN
Platform: UNKNOWN
Classifier: Development Status :: 4 - Beta
Classifier: Environment :: Web Environment
Classifier: Framework :: Django
Classifier: Intended Audience :: Developers
Classifier: License :: OSI Approved :: Apache Software License
Classifier: Programming Language :: Python
Classifier: Operating System :: OS Independent
